grl/__init__.py
grl/agents/__init__.py
grl/agents/base.py
grl/agents/gm.py
grl/agents/idql.py
grl/agents/qgpo.py
grl/agents/srpo.py
grl/algorithms/__init__.py
grl/algorithms/base.py
grl/algorithms/gmpg.py
grl/algorithms/gmpo.py
grl/algorithms/idql.py
grl/algorithms/qgpo.py
grl/algorithms/srpo.py
grl/datasets/__init__.py
grl/datasets/d4rl.py
grl/datasets/gp.py
grl/datasets/minari_dataset.py
grl/datasets/qgpo.py
grl/generative_models/__init__.py
grl/generative_models/diffusion_process.py
grl/generative_models/intrinsic_model.py
grl/generative_models/metric.py
grl/generative_models/random_generator.py
grl/generative_models/sro.py
grl/generative_models/stochastic_process.py
grl/generative_models/variational_autoencoder.py
grl/generative_models/conditional_flow_model/__init__.py
grl/generative_models/conditional_flow_model/guided_conditional_flow_model.py
grl/generative_models/conditional_flow_model/independent_conditional_flow_model.py
grl/generative_models/conditional_flow_model/optimal_transport_conditional_flow_model.py
grl/generative_models/diffusion_model/__init__.py
grl/generative_models/diffusion_model/diffusion_model.py
grl/generative_models/diffusion_model/energy_conditional_diffusion_model.py
grl/generative_models/diffusion_model/guided_diffusion_model.py
grl/generative_models/discrete_model/__init__.py
grl/generative_models/discrete_model/discrete_flow_matching.py
grl/generative_models/model_functions/__init__.py
grl/generative_models/model_functions/data_prediction_function.py
grl/generative_models/model_functions/noise_function.py
grl/generative_models/model_functions/score_function.py
grl/generative_models/model_functions/velocity_function.py
grl/neural_network/__init__.py
grl/neural_network/activation.py
grl/neural_network/encoders.py
grl/neural_network/residual_network.py
grl/neural_network/neural_operator/__init__.py
grl/neural_network/neural_operator/fourier_neural_operator.py
grl/neural_network/transformers/__init__.py
GenerativeRL-0.0.1.dist-info/LICENSE
GenerativeRL-0.0.1.dist-info/METADATA
GenerativeRL-0.0.1.dist-info/WHEEL
GenerativeRL-0.0.1.dist-info/dependency_links.txt
GenerativeRL-0.0.1.dist-info/top_level.txt
GenerativeRL-0.0.1.dist-info/RECORD
