Metadata-Version: 2.1
Name: GenerativeRL
Version: 0.0.1
Summary: PyTorch implementations of generative reinforcement learning algorithms
Home-page: https://github.com/opendilab/GenerativeRL
Author: OpenDILab
Author-email: opendilab@pjlab.org.cn
License: Apache-2.0
Classifier: Programming Language :: Python :: 3
Classifier: Programming Language :: Python :: 3.9
Classifier: Programming Language :: Python :: 3.10
Classifier: Programming Language :: Python :: 3.11
Classifier: Programming Language :: Python :: 3.12
Classifier: License :: OSI Approved :: Apache Software License
Classifier: Operating System :: OS Independent
License-File: LICENSE
Requires-Dist: gym
Requires-Dist: numpy <=1.26.4
Requires-Dist: torch >=2.2.0
Requires-Dist: opencv-python
Requires-Dist: tensordict
Requires-Dist: torchrl
Requires-Dist: di-treetensor
Requires-Dist: matplotlib
Requires-Dist: wandb
Requires-Dist: rich
Requires-Dist: easydict
Requires-Dist: tqdm
Requires-Dist: torchdyn
Requires-Dist: torchsde
Requires-Dist: scipy
Requires-Dist: POT
Requires-Dist: beartype
Requires-Dist: diffusers
Requires-Dist: av
Requires-Dist: moviepy
Requires-Dist: imageio[ffmpeg]
Provides-Extra: di-engine
Requires-Dist: DI-engine ; extra == 'di-engine'
Provides-Extra: d4rl
Requires-Dist: gym ==0.23.1 ; extra == 'd4rl'
Requires-Dist: mujoco-py ; extra == 'd4rl'
Requires-Dist: Cython <3.0 ; extra == 'd4rl'
Provides-Extra: formatter
Requires-Dist: black ; extra == 'formatter'
Requires-Dist: isort ; extra == 'formatter'
